LICENSE
MANIFEST.in
README.md
setup.py
dash/__init__.py
dash/_utils.py
dash/_validate.py
dash/dash.py
dash/dependencies.py
dash/exceptions.py
dash/extract-meta.js
dash/favicon.ico
dash/fingerprint.py
dash/middleware.py
dash/resources.py
dash/urls.py
dash/version.py
dash/views.py
dash/development/__init__.py
dash/development/_all_keywords.py
dash/development/_jl_components_generation.py
dash/development/_py_components_generation.py
dash/development/_r_components_generation.py
dash/development/base_component.py
dash/development/build_process.py
dash/development/component_generator.py
dash/development/component_loader.py
dash/staticfiles/__init__.py
dash/staticfiles/finders.py
dash/templates/dash/base.html
dash/testing/__init__.py
dash/testing/browser.py
dash/testing/composite.py
dash/testing/consts.py
dash/testing/dash_page.py
dash/testing/errors.py
dash/testing/newhooks.py
dash/testing/plugin.py
dash/testing/wait.py
dj_plotly_dash.egg-info/PKG-INFO
dj_plotly_dash.egg-info/SOURCES.txt
dj_plotly_dash.egg-info/dependency_links.txt
dj_plotly_dash.egg-info/entry_points.txt
dj_plotly_dash.egg-info/requires.txt
dj_plotly_dash.egg-info/top_level.txt