Metadata-Version: 2.1
Name: dj-plotly-dash
Version: 0.18.1
Summary: A Python framework for building reactive web-apps. Developed by Plotly.
Home-page: https://github.com/pikhovkin/dj-plotly-dash
Author: Sergei Pikhovkin
Author-email: s@pikhovkin.ru
License: MIT
Platform: UNKNOWN
Classifier: Development Status :: 5 - Production/Stable
Classifier: Environment :: Web Environment
Classifier: Framework :: Dash
Classifier: Framework :: Django
Classifier: Framework :: Django :: 2.0
Classifier: Framework :: Django :: 2.1
Classifier: Framework :: Django :: 2.2
Classifier: Framework :: Django :: 3.1
Classifier: Intended Audience :: Developers
Classifier: Intended Audience :: Education
Classifier: Intended Audience :: Financial and Insurance Industry
Classifier: Intended Audience :: Healthcare Industry
Classifier: Intended Audience :: Manufacturing
Classifier: Intended Audience :: Science/Research
Classifier: License :: OSI Approved :: MIT License
Classifier: Programming Language :: Python
Classifier: Programming Language :: Python :: 3
Classifier: Programming Language :: Python :: 3.7
Classifier: Programming Language :: Python :: 3.8
Classifier: Programming Language :: Python :: 3.9
Classifier: Topic :: Database :: Front-Ends
Classifier: Topic :: Office/Business :: Financial :: Spreadsheet
Classifier: Topic :: Scientific/Engineering :: Visualization
Classifier: Topic :: Software Development :: Libraries :: Application Frameworks
Classifier: Topic :: Software Development :: Widget Sets
Requires-Python: >=2.7, !=3.0.*, !=3.1.*, !=3.2.*
Provides-Extra: all
Provides-Extra: no-dash-renderer
License-File: LICENSE
